fds/__init__.py
fds/sdk/__init__.py
fds/sdk/FactSetSearchAnswers/__init__.py
fds/sdk/FactSetSearchAnswers/api_client.py
fds/sdk/FactSetSearchAnswers/configuration.py
fds/sdk/FactSetSearchAnswers/exceptions.py
fds/sdk/FactSetSearchAnswers/model_utils.py
fds/sdk/FactSetSearchAnswers/rest.py
fds/sdk/FactSetSearchAnswers/api/__init__.py
fds/sdk/FactSetSearchAnswers/api/answers_api.py
fds/sdk/FactSetSearchAnswers/apis/__init__.py
fds/sdk/FactSetSearchAnswers/model/__init__.py
fds/sdk/FactSetSearchAnswers/model/adaptive_card_answer_success_response.py
fds/sdk/FactSetSearchAnswers/model/adaptive_card_data_item.py
fds/sdk/FactSetSearchAnswers/model/adaptive_card_with_thumbnail.py
fds/sdk/FactSetSearchAnswers/model/answer_failure_response.py
fds/sdk/FactSetSearchAnswers/model/answer_with_title.py
fds/sdk/FactSetSearchAnswers/model/answer_with_title_all_of.py
fds/sdk/FactSetSearchAnswers/model/answer_without_data.py
fds/sdk/FactSetSearchAnswers/model/answer_without_data_all_of.py
fds/sdk/FactSetSearchAnswers/model/answer_without_data_all_of_template_data.py
fds/sdk/FactSetSearchAnswers/model/application_link.py
fds/sdk/FactSetSearchAnswers/model/change_color.py
fds/sdk/FactSetSearchAnswers/model/colored_value.py
fds/sdk/FactSetSearchAnswers/model/colored_value_label_date_answer.py
fds/sdk/FactSetSearchAnswers/model/colored_value_label_date_answer_all_of.py
fds/sdk/FactSetSearchAnswers/model/colored_value_label_date_template_data.py
fds/sdk/FactSetSearchAnswers/model/colored_value_label_date_template_data_all_of.py
fds/sdk/FactSetSearchAnswers/model/country_id.py
fds/sdk/FactSetSearchAnswers/model/data_answer.py
fds/sdk/FactSetSearchAnswers/model/data_answer_data.py
fds/sdk/FactSetSearchAnswers/model/data_answer_success_response.py
fds/sdk/FactSetSearchAnswers/model/data_pair.py
fds/sdk/FactSetSearchAnswers/model/error.py
fds/sdk/FactSetSearchAnswers/model/error_link.py
fds/sdk/FactSetSearchAnswers/model/error_source.py
fds/sdk/FactSetSearchAnswers/model/fdc3_context.py
fds.sdk.FactSetSearchAnswers-1.1.7.dist-info/LICENSE
fds.sdk.FactSetSearchAnswers-1.1.7.dist-info/METADATA
fds.sdk.FactSetSearchAnswers-1.1.7.dist-info/WHEEL
fds.sdk.FactSetSearchAnswers-1.1.7.dist-info/top_level.txt
fds.sdk.FactSetSearchAnswers-1.1.7.dist-info/RECORD
